msachin_ashoka/__init__.py
msachin_ashoka-0.1.dist-info/LICENSE
msachin_ashoka-0.1.dist-info/METADATA
msachin_ashoka-0.1.dist-info/WHEEL
msachin_ashoka-0.1.dist-info/top_level.txt
msachin_ashoka-0.1.dist-info/RECORD
