Metadata-Version: 2.1
Name: msachin-ashoka
Version: 0.1
Summary: A sample package
Home-page: https://github.com/sachinashoka/packages.git
Author: Sachin Ashoka
Author-email: sachin.mallade@iiitb.net
License: UNKNOWN
Platform: UNKNOWN
Classifier: Programming Language :: Python :: 3
Classifier: License :: OSI Approved :: MIT License
Classifier: Operating System :: OS Independent
Requires-Dist: requests
